syft_serve/__init__.py
syft_serve/_api.py
syft_serve/_config.py
syft_serve/_endpoint_serializer.py
syft_serve/_environment.py
syft_serve/_exceptions.py
syft_serve/_handle.py
syft_serve/_health.py
syft_serve/_log_stream.py
syft_serve/_manager.py
syft_serve/_process_discovery.py
syft_serve/_process_manager.py
syft_serve/_server.py
syft_serve/_server_collection.py
syft_serve/enhanced_manager.py
syft_serve-0.3.11.dist-info/METADATA
syft_serve-0.3.11.dist-info/WHEEL
syft_serve-0.3.11.dist-info/licenses/LICENSE
syft_serve-0.3.11.dist-info/RECORD
