Metadata-Version: 2.4
Name: syft-serve
Version: 0.3.11
Summary: Generic FastAPI server process management and deduplication
Project-URL: Homepage, https://github.com/OpenMined/syft-serve
Project-URL: Repository, https://github.com/OpenMined/syft-serve
Project-URL: Documentation, https://docs.syft-serve.org
Author-email: OpenMined <info@openmined.org>
License: Apache-2.0
License-File: LICENSE
Classifier: Development Status :: 3 - Alpha
Classifier: Intended Audience :: Developers
Classifier: License :: OSI Approved :: Apache Software License
Classifier: Programming Language :: Python :: 3
Classifier: Programming Language :: Python :: 3.9
Classifier: Programming Language :: Python :: 3.10
Classifier: Programming Language :: Python :: 3.11
Classifier: Programming Language :: Python :: 3.12
Requires-Python: >=3.9
Requires-Dist: fastapi>=0.115.5
Requires-Dist: httpx>=0.25.0
Requires-Dist: jupyter-dark-detect>=0.1.0
Requires-Dist: psutil>=5.9.0
Requires-Dist: pydantic>=2.0.0
Requires-Dist: requests>=2.31.0
Requires-Dist: starlette>=0.41.2
Requires-Dist: tabulate>=0.9.0
Requires-Dist: urllib3>=2.5.0
Requires-Dist: uvicorn[standard]>=0.24.0
Provides-Extra: dev
Requires-Dist: black>=23.0.0; extra == 'dev'
Requires-Dist: mypy>=1.0.0; extra == 'dev'
Requires-Dist: pytest-asyncio>=0.21.0; extra == 'dev'
Requires-Dist: pytest-cov>=4.0.0; extra == 'dev'
Requires-Dist: pytest-mock>=3.10.0; extra == 'dev'
Requires-Dist: pytest-xdist>=3.0.0; extra == 'dev'
Requires-Dist: pytest>=7.0.0; extra == 'dev'
Requires-Dist: ruff>=0.1.0; extra == 'dev'
